scikit_cuda-0.5.3-py3.7-nspkg.pth
scikits/cuda/__init__.py
skcuda/__init__.py
skcuda/autoinit.py
skcuda/cublas.py
skcuda/cublasxt.py
skcuda/cuda.py
skcuda/cudadrv.py
skcuda/cudart.py
skcuda/cufft.py
skcuda/cula.py
skcuda/cusolver.py
skcuda/cusparse.py
skcuda/fft.py
skcuda/info.py
skcuda/integrate.py
skcuda/linalg.py
skcuda/magma.py
skcuda/misc.py
skcuda/pcula.py
skcuda/rlinalg.py
skcuda/special.py
skcuda/utils.py
skcuda/version.py
skcuda/include/cuConstants.h
skcuda/include/cuSpecialFuncs.h
scikit_cuda-0.5.3.dist-info/AUTHORS
scikit_cuda-0.5.3.dist-info/LICENSE
scikit_cuda-0.5.3.dist-info/METADATA
scikit_cuda-0.5.3.dist-info/WHEEL
scikit_cuda-0.5.3.dist-info/namespace_packages.txt
scikit_cuda-0.5.3.dist-info/top_level.txt
scikit_cuda-0.5.3.dist-info/RECORD
