Metadata-Version: 2.1
Name: scikit-cuda
Version: 0.5.3
Summary: Python interface to GPU-powered libraries
Home-page: https://github.com/lebedov/scikit-cuda/
Author: Lev E. Givon
Author-email: lev@columbia.edu
License: BSD
Platform: UNKNOWN
Classifier: Development Status :: 4 - Beta
Classifier: Intended Audience :: Developers
Classifier: Intended Audience :: Science/Research
Classifier: License :: OSI Approved :: BSD License
Classifier: Operating System :: OS Independent
Classifier: Programming Language :: Python
Classifier: Programming Language :: Python :: 2
Classifier: Programming Language :: Python :: 3
Classifier: Topic :: Scientific/Engineering
Classifier: Topic :: Software Development
Provides-Extra: sphinx_rtd_theme
Provides-Extra: sphinx
Provides-Extra: scipy
